collection_sync/__init__.py
collection_sync/util.py
collection_sync/collections/__init__.py
collection_sync/collections/iproute.py
collection_sync/collections/list.py
collection_sync/collections/markdown.py
collection_sync/collections/miniflux.py
collection_sync/collections/yaml.py
collection_sync-0.3.2.dist-info/METADATA
collection_sync-0.3.2.dist-info/WHEEL
collection_sync-0.3.2.dist-info/top_level.txt
collection_sync-0.3.2.dist-info/RECORD
